<mockup version="4.5" minAllowVersion="4.5" ID="95611953-014A-4DDE-BBA5-F92ADB3BDE3F" platform="MtWeb" defaultW="1100" defaultH="6000" measureW="1100" measureH="6000" mobileScreenScale="0">
  <controls controlCount="22">
    <control controlID="18D5A70D-CEFF-4DD9-9FD0-09B21DC7768C" controlTypeID="__group__" isShow="True" caption="%E7%BB%84" x="0" y="0" w="1100" h="817" measuredW="0" measuredH="0" zOrder="0" locked="False" sizeLocked="False">
      <controlProperties>
        <basic color="4294967295" borderVisible="True" borderColor="4284900966" isAutoSize="False" status="MsEnabled" opacity="1" isCommentCom="False" canMove="True" alias="" rotation="0"/>
        <states/>
        <verticalScrollbarShow>False</verticalScrollbarShow>
        <verticalScrollbarProgress>0</verticalScrollbarProgress>
        <horizontalScrollbarShow>False</horizontalScrollbarShow>
        <horizontalScrollbarProgress>0</horizontalScrollbarProgress>
        <links eventType="AtClick" animate="AmNone" animateAutoDelay="0" animateDuration="500">
          <link targetPageID="" linkType="ltPageLink" isApplyIncludePage="False" title="%E9%93%BE%E6%8E%A5">
            <area shape="0" alt="" ID="{3A6230B3-A6BC-45C5-A41D-777404DDC0CE}" coords="(0,0,1100,817)"/>
          </link>
        </links>
        <interactiveData>
          <entry title="">
            <area shape="0" alt="" ID="{F658D553-08AE-4E65-B20A-24979345344A}" coords="(0,0,1100,817)"/>
            <events title=""/>
          </entry>
        </interactiveData>
        <groupChildrenDescriptors>
          <control controlID="CFE25D78-5765-4195-BFA3-9B4BFA5F4D1B" controlTypeID="Shape" isShow="True" caption="%E5%BD%A2%E7%8A%B6" x="0" y="764" w="1100" h="53" measuredW="120" measuredH="100" zOrder="0" locked="False" sizeLocked="False">
            <controlProperties>
              <basic color="4282480272" borderVisible="False" borderColor="4284900966" isAutoSize="False" status="MsEnabled" opacity="1" isCommentCom="False" canMove="True" alias="" rotation="0"/>
              <states/>
              <verticalScrollbarShow>False</verticalScrollbarShow>
              <verticalScrollbarProgress>0</verticalScrollbarProgress>
              <horizontalScrollbarShow>False</horizontalScrollbarShow>
              <horizontalScrollbarProgress>0</horizontalScrollbarProgress>
              <links eventType="AtClick" animate="AmNone" animateAutoDelay="0" animateDuration="500">
                <link targetPageID="" linkType="ltPageLink" isApplyIncludePage="False" title="%E9%93%BE%E6%8E%A5">
                  <area shape="0" alt="" ID="{03261476-E473-4184-8D5A-17922DD31C7F}" coords="(0,0,1100,53)"/>
                </link>
              </links>
              <interactiveData>
                <entry title="">
                  <area shape="0" alt="" ID="{60A06C58-DFDB-4973-AA4F-0D4FB685C8DE}" coords="(0,0,1100,53)"/>
                  <events title=""/>
                </entry>
              </interactiveData>
              <textSet textColor="4294967295" textSize="14" lineSpacingMultiple="1" textAlign="HaLeft" textVAlign="VaMiddle" textWordWrap="True" lineSpacing="18" textStyles="[]" useDefaultTextSize="True">
                <font family="%E5%BE%AE%E8%BD%AF%E9%9B%85%E9%BB%91" displayName="%E5%BE%AE%E8%BD%AF%E9%9B%85%E9%BB%91" postScript="" weightStyle="Regular" weight="400" isBold="False" isItalic="False"/>
                <text>+++++++++++%E7%89%88%E6%9D%83%E6%89%80%E6%9C%89+Copyright@%E7%BE%8E%E5%8D%8E%E5%B0%91%E5%84%BF%E8%8B%B1%E8%AF%AD</text>
              </textSet>
              <selectedIndex>-1</selectedIndex>
              <selectedColor>4291611852</selectedColor>
              <textPadding>0</textPadding>
              <shapeBorderType>SbRectangle</shapeBorderType>
              <triangleType>TdZero</triangleType>
              <dashMode>SdSolid</dashMode>
              <rectangleBorderLeftVisible>True</rectangleBorderLeftVisible>
              <rectangleBorderRightVisible>True</rectangleBorderRightVisible>
              <rectangleBorderTopVisible>True</rectangleBorderTopVisible>
              <rectangleBorderBottomVisible>True</rectangleBorderBottomVisible>
              <radius>0</radius>
              <radiusIsPercent>False</radiusIsPercent>
              <thickness>2</thickness>
            </controlProperties>
          </control>
          <control controlID="940CAF51-D39D-4894-AF96-1A0F5ED0636B" controlTypeID="Shape" isShow="True" caption="%E5%BD%A2%E7%8A%B6" x="0" y="0" w="1100" h="69" measuredW="120" measuredH="100" zOrder="1" locked="False" sizeLocked="False">
            <controlProperties>
              <basic color="4282480272" borderVisible="False" borderColor="4284900966" isAutoSize="False" status="MsEnabled" opacity="1" isCommentCom="False" canMove="True" alias="" rotation="0"/>
              <states/>
              <verticalScrollbarShow>False</verticalScrollbarShow>
              <verticalScrollbarProgress>0</verticalScrollbarProgress>
              <horizontalScrollbarShow>False</horizontalScrollbarShow>
              <horizontalScrollbarProgress>0</horizontalScrollbarProgress>
              <links eventType="AtClick" animate="AmNone" animateAutoDelay="0" animateDuration="500">
                <link targetPageID="" linkType="ltPageLink" isApplyIncludePage="False" title="%E9%93%BE%E6%8E%A5">
                  <area shape="0" alt="" ID="{BF92726E-635B-46C6-8147-163238A5737B}" coords="(0,0,1100,69)"/>
                </link>
              </links>
              <interactiveData>
                <entry title="">
                  <area shape="0" alt="" ID="{13321093-3D51-48D7-B396-B8EB3E83E58C}" coords="(0,0,1100,69)"/>
                  <events title=""/>
                </entry>
              </interactiveData>
              <textSet textColor="4294303069" textSize="26" lineSpacingMultiple="1" textAlign="HaLeft" textVAlign="VaMiddle" textWordWrap="True" lineSpacing="34" textStyles="[]" useDefaultTextSize="False">
                <font family="%E5%BE%AE%E8%BD%AF%E9%9B%85%E9%BB%91" displayName="%E5%BE%AE%E8%BD%AF%E9%9B%85%E9%BB%91" postScript="" weightStyle="Regular" weight="400" isBold="False" isItalic="False"/>
                <text>+++++%E7%BE%8E%E5%8D%8E%E5%B0%91%E5%84%BF%E8%8B%B1%E8%AF%AD</text>
              </textSet>
              <selectedIndex>-1</selectedIndex>
              <selectedColor>4291611852</selectedColor>
              <textPadding>0</textPadding>
              <shapeBorderType>SbRectangle</shapeBorderType>
              <triangleType>TdZero</triangleType>
              <dashMode>SdSolid</dashMode>
              <rectangleBorderLeftVisible>True</rectangleBorderLeftVisible>
              <rectangleBorderRightVisible>True</rectangleBorderRightVisible>
              <rectangleBorderTopVisible>True</rectangleBorderTopVisible>
              <rectangleBorderBottomVisible>True</rectangleBorderBottomVisible>
              <radius>0</radius>
              <radiusIsPercent>False</radiusIsPercent>
              <thickness>2</thickness>
            </controlProperties>
          </control>
        </groupChildrenDescriptors>
      </controlProperties>
    </control>
    <control controlID="5721ECAD-78AE-445D-8A94-09D35C98FE82" controlTypeID="Shape" isShow="True" caption="%E5%BD%A2%E7%8A%B6" x="0" y="69" w="1100" h="53" measuredW="120" measuredH="100" zOrder="1" locked="False" sizeLocked="False">
      <controlProperties>
        <basic color="4294506744" borderVisible="False" borderColor="4284900966" isAutoSize="False" status="MsEnabled" opacity="1" isCommentCom="False" canMove="True" alias="" rotation="0"/>
        <states/>
        <verticalScrollbarShow>False</verticalScrollbarShow>
        <verticalScrollbarProgress>0</verticalScrollbarProgress>
        <horizontalScrollbarShow>False</horizontalScrollbarShow>
        <horizontalScrollbarProgress>0</horizontalScrollbarProgress>
        <links eventType="AtClick" animate="AmNone" animateAutoDelay="0" animateDuration="500">
          <link targetPageID="" linkType="ltPageLink" isApplyIncludePage="False" title="%E9%93%BE%E6%8E%A5">
            <area shape="0" alt="" ID="{4B0C01C7-1D83-41DB-B9A8-149312B2264D}" coords="(0,0,1100,53)"/>
          </link>
        </links>
        <interactiveData>
          <entry title="">
            <area shape="0" alt="" ID="{733DB88B-6F9B-46BA-A36F-FA0D92F2AB31}" coords="(0,0,1100,53)"/>
            <events title=""/>
          </entry>
        </interactiveData>
        <textSet textColor="4278190080" textSize="14" lineSpacingMultiple="1" textAlign="HaCenter" textVAlign="VaMiddle" textWordWrap="True" lineSpacing="18" textStyles="[]" useDefaultTextSize="True">
          <font family="%E5%BE%AE%E8%BD%AF%E9%9B%85%E9%BB%91" displayName="%E5%BE%AE%E8%BD%AF%E9%9B%85%E9%BB%91" postScript="" weightStyle="Regular" weight="400" isBold="False" isItalic="False"/>
        </textSet>
        <selectedIndex>-1</selectedIndex>
        <selectedColor>4282501083</selectedColor>
        <textPadding>0</textPadding>
        <shapeBorderType>SbRectangle</shapeBorderType>
        <triangleType>TdZero</triangleType>
        <dashMode>SdSolid</dashMode>
        <rectangleBorderLeftVisible>True</rectangleBorderLeftVisible>
        <rectangleBorderRightVisible>True</rectangleBorderRightVisible>
        <rectangleBorderTopVisible>True</rectangleBorderTopVisible>
        <rectangleBorderBottomVisible>True</rectangleBorderBottomVisible>
        <radius>0</radius>
        <radiusIsPercent>False</radiusIsPercent>
        <thickness>1</thickness>
      </controlProperties>
    </control>
    <control controlID="59343808-7066-491A-ACE6-328EF3F36A67" controlTypeID="Icon" isShow="True" caption="%E5%9B%BE%E6%A0%87" x="20" y="84" w="24" h="24" measuredW="24" measuredH="24" zOrder="2" locked="False" sizeLocked="False">
      <controlProperties>
        <basic color="4284900966" borderVisible="True" borderColor="4284900966" isAutoSize="False" status="MsEnabled" opacity="1" isCommentCom="False" canMove="True" alias="" rotation="0"/>
        <states/>
        <verticalScrollbarShow>False</verticalScrollbarShow>
        <verticalScrollbarProgress>0</verticalScrollbarProgress>
        <horizontalScrollbarShow>False</horizontalScrollbarShow>
        <horizontalScrollbarProgress>0</horizontalScrollbarProgress>
        <links eventType="AtClick" animate="AmNone" animateAutoDelay="0" animateDuration="500">
          <link targetPageID="" linkType="ltPageLink" isApplyIncludePage="False" title="%E9%93%BE%E6%8E%A5">
            <area shape="0" alt="" ID="{107C0EF0-8CDB-461B-BA8C-C7E70D8E1356}" coords="(0,0,24,24)"/>
          </link>
        </links>
        <interactiveData>
          <entry title="">
            <area shape="0" alt="" ID="{7A1F1F37-A725-42AC-9F1D-0434C894B00A}" coords="(0,0,24,24)"/>
            <events title=""/>
          </entry>
        </interactiveData>
        <rotationAngle>TdZero</rotationAngle>
        <icon>
          <ID/>
          <iconFontName>jdIonicons</iconFontName>
          <iconCode>62197</iconCode>
        </icon>
        <URL>3A3CD3DB2FAE85FFEF2A8996E634645D.svg</URL>
        <FlipHorizontal>False</FlipHorizontal>
        <FlipVertical>False</FlipVertical>
      </controlProperties>
    </control>
    <control controlID="06962570-5A7B-46B7-8EFE-B3DE6FC1FE0A" controlTypeID="Shape" isShow="True" caption="%E5%BD%A2%E7%8A%B6" x="57" y="82" w="338" h="29" measuredW="120" measuredH="100" zOrder="3" locked="False" sizeLocked="False">
      <controlProperties>
        <basic color="4294967295" borderVisible="True" borderColor="4284900966" isAutoSize="False" status="MsEnabled" opacity="1" isCommentCom="False" canMove="True" alias="" rotation="0"/>
        <states/>
        <verticalScrollbarShow>False</verticalScrollbarShow>
        <verticalScrollbarProgress>0</verticalScrollbarProgress>
        <horizontalScrollbarShow>False</horizontalScrollbarShow>
        <horizontalScrollbarProgress>0</horizontalScrollbarProgress>
        <links eventType="AtClick" animate="AmNone" animateAutoDelay="0" animateDuration="500">
          <link targetPageID="" linkType="ltPageLink" isApplyIncludePage="False" title="%E9%93%BE%E6%8E%A5">
            <area shape="0" alt="" ID="{CEF4901D-8519-4E61-8692-0F2D5A77B9C3}" coords="(0,0,338,29)"/>
          </link>
        </links>
        <interactiveData>
          <entry title="">
            <area shape="0" alt="" ID="{F0FFCE61-4171-4118-B83C-427B4FEB46A7}" coords="(0,0,338,29)"/>
            <events title=""/>
          </entry>
        </interactiveData>
        <textSet textColor="4278190080" textSize="14" lineSpacingMultiple="1" textAlign="HaLeft" textVAlign="VaMiddle" textWordWrap="True" lineSpacing="18" textStyles="[]" useDefaultTextSize="True">
          <font family="%E5%BE%AE%E8%BD%AF%E9%9B%85%E9%BB%91" displayName="%E5%BE%AE%E8%BD%AF%E9%9B%85%E9%BB%91" postScript="" weightStyle="Regular" weight="400" isBold="False" isItalic="False"/>
          <text>++++%E6%9D%8E%E9%98%B3</text>
        </textSet>
        <selectedIndex>-1</selectedIndex>
        <selectedColor>4282501083</selectedColor>
        <textPadding>0</textPadding>
        <shapeBorderType>SbRectangle</shapeBorderType>
        <triangleType>TdZero</triangleType>
        <dashMode>SdSolid</dashMode>
        <rectangleBorderLeftVisible>True</rectangleBorderLeftVisible>
        <rectangleBorderRightVisible>True</rectangleBorderRightVisible>
        <rectangleBorderTopVisible>True</rectangleBorderTopVisible>
        <rectangleBorderBottomVisible>True</rectangleBorderBottomVisible>
        <radius>4</radius>
        <radiusIsPercent>False</radiusIsPercent>
        <thickness>1</thickness>
      </controlProperties>
    </control>
    <control controlID="BC6A97F3-5523-4993-B387-484C55715DC9" controlTypeID="Shape" isShow="True" caption="%E5%BD%A2%E7%8A%B6" x="405" y="82" w="78" h="29" measuredW="120" measuredH="100" zOrder="4" locked="False" sizeLocked="False">
      <controlProperties>
        <basic color="4294769916" borderVisible="True" borderColor="4284900966" isAutoSize="False" status="MsEnabled" opacity="1" isCommentCom="False" canMove="True" alias="" rotation="0"/>
        <states/>
        <verticalScrollbarShow>False</verticalScrollbarShow>
        <verticalScrollbarProgress>0</verticalScrollbarProgress>
        <horizontalScrollbarShow>False</horizontalScrollbarShow>
        <horizontalScrollbarProgress>0</horizontalScrollbarProgress>
        <links eventType="AtClick" animate="AmNone" animateAutoDelay="0" animateDuration="500">
          <link targetPageID="" linkType="ltPageLink" isApplyIncludePage="False" title="%E9%93%BE%E6%8E%A5">
            <area shape="0" alt="" ID="{6D46BA54-05EE-4105-B54B-609BBA199F11}" coords="(0,0,78,29)"/>
          </link>
        </links>
        <interactiveData>
          <entry title="">
            <area shape="0" alt="" ID="{8CA9F309-5D63-401B-854D-CA473DB9789E}" coords="(0,0,78,29)"/>
            <events title=""/>
          </entry>
        </interactiveData>
        <textSet textColor="4278190080" textSize="14" lineSpacingMultiple="1" textAlign="HaCenter" textVAlign="VaMiddle" textWordWrap="True" lineSpacing="18" textStyles="[]" useDefaultTextSize="True">
          <font family="%E5%BE%AE%E8%BD%AF%E9%9B%85%E9%BB%91" displayName="%E5%BE%AE%E8%BD%AF%E9%9B%85%E9%BB%91" postScript="" weightStyle="Regular" weight="400" isBold="False" isItalic="False"/>
          <text>%E6%90%9C%E7%B4%A2</text>
        </textSet>
        <selectedIndex>-1</selectedIndex>
        <selectedColor>4282501083</selectedColor>
        <textPadding>0</textPadding>
        <shapeBorderType>SbRectangle</shapeBorderType>
        <triangleType>TdZero</triangleType>
        <dashMode>SdSolid</dashMode>
        <rectangleBorderLeftVisible>True</rectangleBorderLeftVisible>
        <rectangleBorderRightVisible>True</rectangleBorderRightVisible>
        <rectangleBorderTopVisible>True</rectangleBorderTopVisible>
        <rectangleBorderBottomVisible>True</rectangleBorderBottomVisible>
        <radius>4</radius>
        <radiusIsPercent>False</radiusIsPercent>
        <thickness>1</thickness>
      </controlProperties>
    </control>
    <control controlID="47ED55A4-5DE6-4D4B-B721-080CEFBC79FB" controlTypeID="Shape" isShow="True" caption="%E5%BD%A2%E7%8A%B6" x="1002" y="81" w="78" h="29" measuredW="120" measuredH="100" zOrder="5" locked="False" sizeLocked="False">
      <controlProperties>
        <basic color="4281571737" borderVisible="True" borderColor="4284900966" isAutoSize="False" status="MsEnabled" opacity="1" isCommentCom="False" canMove="True" alias="" rotation="0"/>
        <states/>
        <verticalScrollbarShow>False</verticalScrollbarShow>
        <verticalScrollbarProgress>0</verticalScrollbarProgress>
        <horizontalScrollbarShow>False</horizontalScrollbarShow>
        <horizontalScrollbarProgress>0</horizontalScrollbarProgress>
        <links eventType="AtClick" animate="AmNone" animateAutoDelay="0" animateDuration="500">
          <link targetPageID="D90C09EE-832B-492F-AEAA-100B4AE0564F" linkType="ltPageLink" isApplyIncludePage="False" title="Add_user">
            <area shape="0" alt="" ID="{6D46BA54-05EE-4105-B54B-609BBA199F11}" coords="(0,0,78,29)"/>
          </link>
        </links>
        <interactiveData>
          <entry title="">
            <area shape="0" alt="" ID="{8CA9F309-5D63-401B-854D-CA473DB9789E}" coords="(0,0,78,29)"/>
            <events title=""/>
          </entry>
        </interactiveData>
        <textSet textColor="4278190080" textSize="14" lineSpacingMultiple="1" textAlign="HaCenter" textVAlign="VaMiddle" textWordWrap="True" lineSpacing="18" textStyles="[]" useDefaultTextSize="True">
          <font family="%E5%BE%AE%E8%BD%AF%E9%9B%85%E9%BB%91" displayName="%E5%BE%AE%E8%BD%AF%E9%9B%85%E9%BB%91" postScript="" weightStyle="Regular" weight="400" isBold="False" isItalic="False"/>
          <text>%E5%88%9B%E5%BB%BA%E5%B8%90%E5%8F%B7</text>
        </textSet>
        <selectedIndex>-1</selectedIndex>
        <selectedColor>4282501083</selectedColor>
        <textPadding>0</textPadding>
        <shapeBorderType>SbRectangle</shapeBorderType>
        <triangleType>TdZero</triangleType>
        <dashMode>SdSolid</dashMode>
        <rectangleBorderLeftVisible>True</rectangleBorderLeftVisible>
        <rectangleBorderRightVisible>True</rectangleBorderRightVisible>
        <rectangleBorderTopVisible>True</rectangleBorderTopVisible>
        <rectangleBorderBottomVisible>True</rectangleBorderBottomVisible>
        <radius>4</radius>
        <radiusIsPercent>False</radiusIsPercent>
        <thickness>1</thickness>
      </controlProperties>
    </control>
    <control controlID="445D4E3E-90D4-4636-94F6-F71F302F9B16" controlTypeID="DataGrid" isShow="True" caption="%E8%A1%A8%E6%A0%BC" x="0" y="120" w="1100" h="601" measuredW="260" measuredH="192" zOrder="6" locked="False" sizeLocked="False">
      <controlProperties>
        <basic color="4294967295" borderVisible="True" borderColor="4284900966" isAutoSize="False" status="MsEnabled" opacity="1" isCommentCom="False" canMove="True" alias="" rotation="0"/>
        <states/>
        <verticalScrollbarShow>False</verticalScrollbarShow>
        <verticalScrollbarProgress>0</verticalScrollbarProgress>
        <horizontalScrollbarShow>False</horizontalScrollbarShow>
        <horizontalScrollbarProgress>0</horizontalScrollbarProgress>
        <links eventType="AtClick" animate="AmNone" animateAutoDelay="0" animateDuration="500">
          <link targetPageID="" linkType="ltPageLink" isApplyIncludePage="False" title="%E5%A7%93%E5%90%8D+%5Ev%2C+%E8%8B%B1%E6%96%87%E5%90%8D+%5E%2C%E5%AD%A6%E5%8F%B7+%5Ev%2C%E6%80%A7%E5%88%AB+%5Ev%2C+%E6%89%8B%E6%9C%BA%E5%8F%B7%E7%A0%81%2C%E9%82%AE%E7%AE%B1%2C+%E6%A0%A1%E5%8C%BA+%5Ev%2C%E6%9D%83%E9%99%90+v%2C%E5%88%9B%E5%BB%BA%E6%97%B6%E9%97%B4+%5Ev%2C%E6%9C%80%E8%BF%91%E7%99%BB%E5%BD%95+%5Ev+">
            <area shape="0" alt="" ID="{D9507AB7-7DD1-43C6-B797-07874C8441E7}" coords="(0,0.00999999977648258,1100,22.0100002288818)"/>
          </link>
          <link targetPageID="AC04CEF9-39DA-4C2B-AB17-157CBC4E064B" linkType="ltPageLink" isApplyIncludePage="False" title="%E5%BC%A0%E4%B8%89%2C+zhang+san%2C10000%2C%E7%94%B7%2C152xxxx1234%2Cxxx@xxx.com%2C+%E6%80%BB%E9%83%A8%2C%E8%B6%85%E7%BA%A7%E7%AE%A1%E7%90%86%E5%91%98%2C2017-03-11+10%3A30%3A12%2C2017-03-11+11%3A40%3A12">
            <area shape="0" alt="" ID="{785F7104-C2C6-4F76-B64B-82A9C3F50C8E}" coords="(0,22,1100,62)"/>
          </link>
          <link targetPageID="AC04CEF9-39DA-4C2B-AB17-157CBC4E064B" linkType="ltPageLink" isApplyIncludePage="False" title="%E6%9D%8E%E5%9B%9B%2Cli+si%2C10001%2C%E5%A5%B3%2C152xxxx1234%2Cxxx@xxx.com%2C+%E4%B8%8A%E6%B5%B71%E5%8C%BA%2C%E6%A0%A1%E5%8C%BA%E7%AE%A1%E7%90%86%E5%91%98%2C2017-03-11+10%3A30%3A12%2C2017-03-11+11%3A40%3A12">
            <area shape="0" alt="" ID="{0D6A2C6A-30B5-4CED-A5B9-A654D38F5CC3}" coords="(0,62,1100,102)"/>
          </link>
          <link targetPageID="AC04CEF9-39DA-4C2B-AB17-157CBC4E064B" linkType="ltPageLink" isApplyIncludePage="False" title="%E7%8E%8B%E4%BA%94%2Cwang+wu%2C10002%2C%E7%94%B7%2C+152xxxx1234%2Cxxx@xxx.com%2C%E4%B8%8A%E6%B5%B72%E5%8C%BA%2C%E8%80%81%E5%B8%88%2C2017-03-11+10%3A30%3A12%2C2017-03-11+11%3A40%3A12">
            <area shape="0" alt="" ID="{F05DD598-E75D-4DDC-97A7-7E43D26108F4}" coords="(0,102,1100,142)"/>
          </link>
          <link targetPageID="" linkType="ltPageLink" isApplyIncludePage="False" title="%E8%B5%B5%E5%85%AD%2Czhaoliu%2C10003%2C+%3A)%2C152xxxx1234%2Cxxx@xxx.com%2C%E5%A8%81%E6%B5%B7%2C%E5%AD%A6%E7%94%9F%2C2017-03-11+10%3A30%3A12">
            <area shape="0" alt="" ID="{D8227992-5C11-4B1B-A947-560E165B31D6}" coords="(0,142,1100,182)"/>
          </link>
          <link targetPageID="" linkType="ltPageLink" isApplyIncludePage="False" title="%E5%91%A8%E4%B8%83%2Czhouqi%2C10004%2C%3A)%2C152xxxx1234%2Cxxx@xxx.com%2C%E6%B1%9F%E8%8B%8F%2C%E5%AD%A6%E7%94%9F%2C2017-03-11+10%3A30%3A12%2C2017-03-11+11%3A40%3A12">
            <area shape="0" alt="" ID="{13B0B6F8-F6A2-4220-91C9-B71D3DC644AE}" coords="(0,182,1100,222)"/>
          </link>
          <link targetPageID="" linkType="ltPageLink" isApplyIncludePage="False" title="%E5%BC%A0%E4%B8%89%2C+zhang+san%2C10000%2C%E7%94%B7%2C152xxxx1234%2Cxxx@xxx.com%2C+%E6%80%BB%E9%83%A8%2C%E8%B6%85%E7%BA%A7%E7%AE%A1%E7%90%86%E5%91%98%2C2017-03-11+10%3A30%3A12%2C2017-03-11+11%3A40%3A12">
            <area shape="0" alt="" ID="{20757CDD-BF69-421C-B404-45D813E6DB93}" coords="(0,222,1100,262)"/>
          </link>
          <link targetPageID="" linkType="ltPageLink" isApplyIncludePage="False" title="%E6%9D%8E%E5%9B%9B%2Cli+si%2C10001%2C%E5%A5%B3%2C152xxxx1234%2Cxxx@xxx.com%2C+%E4%B8%8A%E6%B5%B71%E5%8C%BA%2C%E6%A0%A1%E5%8C%BA%E7%AE%A1%E7%90%86%E5%91%98%2C2017-03-11+10%3A30%3A12%2C2017-03-11+11%3A40%3A12">
            <area shape="0" alt="" ID="{B1766BBC-31B9-4E96-842F-7AE2F4879B54}" coords="(0,262,1100,302)"/>
          </link>
          <link targetPageID="" linkType="ltPageLink" isApplyIncludePage="False" title="%E7%8E%8B%E4%BA%94%2Cwang+wu%2C10002%2C%E7%94%B7%2C+152xxxx1234%2Cxxx@xxx.com%2C%E4%B8%8A%E6%B5%B72%E5%8C%BA%2C%E8%80%81%E5%B8%88%2C2017-03-11+10%3A30%3A12%2C2017-03-11+11%3A40%3A12">
            <area shape="0" alt="" ID="{475E777A-AAA7-4918-9E60-2851F6307DDD}" coords="(0,302,1100,342)"/>
          </link>
          <link targetPageID="" linkType="ltPageLink" isApplyIncludePage="False" title="%E8%B5%B5%E5%85%AD%2Czhaoliu%2C10003%2C+%3A)%2C152xxxx1234%2Cxxx@xxx.com%2C%E5%A8%81%E6%B5%B7%2C%E5%AD%A6%E7%94%9F%2C2017-03-11+10%3A30%3A12">
            <area shape="0" alt="" ID="{709FDDB5-5F12-4896-BE42-F0D860F9248C}" coords="(0,342,1100,382)"/>
          </link>
          <link targetPageID="" linkType="ltPageLink" isApplyIncludePage="False" title="%E5%91%A8%E4%B8%83%2Czhouqi%2C10004%2C%3A)%2C152xxxx1234%2Cxxx@xxx.com%2C%E6%B1%9F%E8%8B%8F%2C%E5%AD%A6%E7%94%9F%2C2017-03-11+10%3A30%3A12%2C2017-03-11+11%3A40%3A12">
            <area shape="0" alt="" ID="{D3EDDE6E-E38A-4916-B067-B9F25100FAF9}" coords="(0,382,1100,422)"/>
          </link>
          <link targetPageID="" linkType="ltPageLink" isApplyIncludePage="False" title="%E6%9D%8E%E5%9B%9B%2Cli+si%2C10001%2C%E5%A5%B3%2C152xxxx1234%2Cxxx@xxx.com%2C+%E4%B8%8A%E6%B5%B71%E5%8C%BA%2C%E6%A0%A1%E5%8C%BA%E7%AE%A1%E7%90%86%E5%91%98%2C2017-03-11+10%3A30%3A12%2C2017-03-11+11%3A40%3A12">
            <area shape="0" alt="" ID="{0FC3DAE3-1A2F-491E-82CD-ED25587B5A86}" coords="(0,422,1100,462)"/>
          </link>
          <link targetPageID="" linkType="ltPageLink" isApplyIncludePage="False" title="%E7%8E%8B%E4%BA%94%2Cwang+wu%2C10002%2C%E7%94%B7%2C+152xxxx1234%2Cxxx@xxx.com%2C%E4%B8%8A%E6%B5%B72%E5%8C%BA%2C%E8%80%81%E5%B8%88%2C2017-03-11+10%3A30%3A12%2C2017-03-11+11%3A40%3A12">
            <area shape="0" alt="" ID="{8F2F340C-8AAF-4BA5-876E-470A7F02675B}" coords="(0,462,1100,502)"/>
          </link>
          <link targetPageID="" linkType="ltPageLink" isApplyIncludePage="False" title="%E8%B5%B5%E5%85%AD%2Czhaoliu%2C10003%2C+%3A)%2C152xxxx1234%2Cxxx@xxx.com%2C%E5%A8%81%E6%B5%B7%2C%E5%AD%A6%E7%94%9F%2C2017-03-11+10%3A30%3A12">
            <area shape="0" alt="" ID="{E9BEC5DD-7353-4641-B2F8-4568CCCB22CE}" coords="(0,502,1100,542)"/>
          </link>
          <link targetPageID="" linkType="ltPageLink" isApplyIncludePage="False" title="%E5%91%A8%E4%B8%83%2Czhouqi%2C10004%2C%3A)%2C152xxxx1234%2Cxxx@xxx.com%2C%E6%B1%9F%E8%8B%8F%2C%E5%AD%A6%E7%94%9F%2C2017-03-11+10%3A30%3A12%2C2017-03-11+11%3A40%3A12">
            <area shape="0" alt="" ID="{D28A2A3B-0779-4C3C-B72A-6C062A857B59}" coords="(0,542,1100,582)"/>
          </link>
          <link targetPageID="" linkType="ltPageLink" isApplyIncludePage="False" title="%E5%BC%A0%E4%B8%89%2C+zhang+san%2C10000%2C%E7%94%B7%2C152xxxx1234%2Cxxx@xxx.com%2C+%E6%80%BB%E9%83%A8%2C%E8%B6%85%E7%BA%A7%E7%AE%A1%E7%90%86%E5%91%98%2C2017-03-11+10%3A30%3A12%2C2017-03-11+11%3A40%3A12">
            <area shape="0" alt="" ID="{5B81F647-8FE2-4C17-8CC2-4FC40194B006}" coords="(0,582,1100,601)"/>
          </link>
          <link targetPageID="" linkType="ltPageLink" isApplyIncludePage="False" title="%E6%9D%8E%E5%9B%9B%2Cli+si%2C10001%2C%E5%A5%B3%2C152xxxx1234%2Cxxx@xxx.com%2C+%E4%B8%8A%E6%B5%B71%E5%8C%BA%2C%E6%A0%A1%E5%8C%BA%E7%AE%A1%E7%90%86%E5%91%98%2C2017-03-11+10%3A30%3A12%2C2017-03-11+11%3A40%3A12">
            <area shape="0" alt="" ID="{67F388C4-2B25-43AE-ACC2-B26F30842348}" coords="(0,0,0,0)"/>
          </link>
          <link targetPageID="" linkType="ltPageLink" isApplyIncludePage="False" title="%E7%8E%8B%E4%BA%94%2Cwang+wu%2C10002%2C%E7%94%B7%2C+152xxxx1234%2Cxxx@xxx.com%2C%E4%B8%8A%E6%B5%B72%E5%8C%BA%2C%E8%80%81%E5%B8%88%2C2017-03-11+10%3A30%3A12%2C2017-03-11+11%3A40%3A12">
            <area shape="0" alt="" ID="{07BA1E2E-3C61-4533-A6B6-957B54DA7173}" coords="(0,0,0,0)"/>
          </link>
          <link targetPageID="" linkType="ltPageLink" isApplyIncludePage="False" title="%E8%B5%B5%E5%85%AD%2Czhaoliu%2C10003%2C+%3A)%2C152xxxx1234%2Cxxx@xxx.com%2C%E5%A8%81%E6%B5%B7%2C%E5%AD%A6%E7%94%9F%2C2017-03-11+10%3A30%3A12">
            <area shape="0" alt="" ID="{7D123234-DA6B-417C-8365-495CDE2AE5AE}" coords="(0,0,0,0)"/>
          </link>
          <link targetPageID="" linkType="ltPageLink" isApplyIncludePage="False" title="%E5%91%A8%E4%B8%83%2Czhouqi%2C10004%2C%3A)%2C152xxxx1234%2Cxxx@xxx.com%2C%E6%B1%9F%E8%8B%8F%2C%E5%AD%A6%E7%94%9F%2C2017-03-11+10%3A30%3A12%2C2017-03-11+11%3A40%3A12">
            <area shape="0" alt="" ID="{DF135A65-CEE8-4146-8B46-3B343DB7E046}" coords="(0,0,0,0)"/>
          </link>
        </links>
        <interactiveData>
          <entry title="%E5%A7%93%E5%90%8D+%5Ev%2C+%E8%8B%B1%E6%96%87%E5%90%8D+%5E%2C%E5%AD%A6%E5%8F%B7+%5Ev%2C%E6%80%A7%E5%88%AB+%5Ev%2C+%E6%89%8B%E6%9C%BA%E5%8F%B7%E7%A0%81%2C%E9%82%AE%E7%AE%B1%2C+%E6%A0%A1%E5%8C%BA+%5Ev%2C%E6%9D%83%E9%99%90+v%2C%E5%88%9B%E5%BB%BA%E6%97%B6%E9%97%B4+%5Ev%2C%E6%9C%80%E8%BF%91%E7%99%BB%E5%BD%95+%5Ev+">
            <area shape="0" alt="" ID="{043305AE-8CB0-4B80-83CD-D5159AE5BD8E}" coords="(0,0.00999999977648258,1100,22.0100002288818)"/>
            <events title=""/>
          </entry>
          <entry title="%E5%BC%A0%E4%B8%89%2C+zhang+san%2C10000%2C%E7%94%B7%2C152xxxx1234%2Cxxx@xxx.com%2C+%E6%80%BB%E9%83%A8%2C%E8%B6%85%E7%BA%A7%E7%AE%A1%E7%90%86%E5%91%98%2C2017-03-11+10%3A30%3A12%2C2017-03-11+11%3A40%3A12">
            <area shape="0" alt="" ID="{F92EF581-CEB1-482B-BBD6-9F0445310AE2}" coords="(0,22,1100,62)"/>
            <events title=""/>
          </entry>
          <entry title="%E6%9D%8E%E5%9B%9B%2Cli+si%2C10001%2C%E5%A5%B3%2C152xxxx1234%2Cxxx@xxx.com%2C+%E4%B8%8A%E6%B5%B71%E5%8C%BA%2C%E6%A0%A1%E5%8C%BA%E7%AE%A1%E7%90%86%E5%91%98%2C2017-03-11+10%3A30%3A12%2C2017-03-11+11%3A40%3A12">
            <area shape="0" alt="" ID="{BF2CE047-3AAC-4768-9B53-9B9ADAE9745D}" coords="(0,62,1100,102)"/>
            <events title=""/>
          </entry>
          <entry title="%E7%8E%8B%E4%BA%94%2Cwang+wu%2C10002%2C%E7%94%B7%2C+152xxxx1234%2Cxxx@xxx.com%2C%E4%B8%8A%E6%B5%B72%E5%8C%BA%2C%E8%80%81%E5%B8%88%2C2017-03-11+10%3A30%3A12%2C2017-03-11+11%3A40%3A12">
            <area shape="0" alt="" ID="{A5D9A90E-54F9-4415-A3AE-D140884C05A3}" coords="(0,102,1100,142)"/>
            <events title=""/>
          </entry>
          <entry title="%E8%B5%B5%E5%85%AD%2Czhaoliu%2C10003%2C+%3A)%2C152xxxx1234%2Cxxx@xxx.com%2C%E5%A8%81%E6%B5%B7%2C%E5%AD%A6%E7%94%9F%2C2017-03-11+10%3A30%3A12">
            <area shape="0" alt="" ID="{EA8DA4D1-9947-4706-8318-5C6316DA5320}" coords="(0,142,1100,182)"/>
            <events title=""/>
          </entry>
          <entry title="%E5%91%A8%E4%B8%83%2Czhouqi%2C10004%2C%3A)%2C152xxxx1234%2Cxxx@xxx.com%2C%E6%B1%9F%E8%8B%8F%2C%E5%AD%A6%E7%94%9F%2C2017-03-11+10%3A30%3A12%2C2017-03-11+11%3A40%3A12">
            <area shape="0" alt="" ID="{5F0DD531-DED3-4BD8-A839-E0AB5363F125}" coords="(0,182,1100,222)"/>
            <events title=""/>
          </entry>
          <entry title="%E5%BC%A0%E4%B8%89%2C+zhang+san%2C10000%2C%E7%94%B7%2C152xxxx1234%2Cxxx@xxx.com%2C+%E6%80%BB%E9%83%A8%2C%E8%B6%85%E7%BA%A7%E7%AE%A1%E7%90%86%E5%91%98%2C2017-03-11+10%3A30%3A12%2C2017-03-11+11%3A40%3A12">
            <area shape="0" alt="" ID="{C10250FC-F957-4605-BB76-C22FD0782B0F}" coords="(0,222,1100,262)"/>
            <events title=""/>
          </entry>
          <entry title="%E6%9D%8E%E5%9B%9B%2Cli+si%2C10001%2C%E5%A5%B3%2C152xxxx1234%2Cxxx@xxx.com%2C+%E4%B8%8A%E6%B5%B71%E5%8C%BA%2C%E6%A0%A1%E5%8C%BA%E7%AE%A1%E7%90%86%E5%91%98%2C2017-03-11+10%3A30%3A12%2C2017-03-11+11%3A40%3A12">
            <area shape="0" alt="" ID="{10101221-91D6-4DFE-942B-8713A48B6110}" coords="(0,262,1100,302)"/>
            <events title=""/>
          </entry>
          <entry title="%E7%8E%8B%E4%BA%94%2Cwang+wu%2C10002%2C%E7%94%B7%2C+152xxxx1234%2Cxxx@xxx.com%2C%E4%B8%8A%E6%B5%B72%E5%8C%BA%2C%E8%80%81%E5%B8%88%2C2017-03-11+10%3A30%3A12%2C2017-03-11+11%3A40%3A12">
            <area shape="0" alt="" ID="{3BB42FEA-0126-4236-8267-FA8487FCA1EF}" coords="(0,302,1100,342)"/>
            <events title=""/>
          </entry>
          <entry title="%E8%B5%B5%E5%85%AD%2Czhaoliu%2C10003%2C+%3A)%2C152xxxx1234%2Cxxx@xxx.com%2C%E5%A8%81%E6%B5%B7%2C%E5%AD%A6%E7%94%9F%2C2017-03-11+10%3A30%3A12">
            <area shape="0" alt="" ID="{ADA0E885-3A1C-4541-9692-7E539D111E74}" coords="(0,342,1100,382)"/>
            <events title=""/>
          </entry>
          <entry title="%E5%91%A8%E4%B8%83%2Czhouqi%2C10004%2C%3A)%2C152xxxx1234%2Cxxx@xxx.com%2C%E6%B1%9F%E8%8B%8F%2C%E5%AD%A6%E7%94%9F%2C2017-03-11+10%3A30%3A12%2C2017-03-11+11%3A40%3A12">
            <area shape="0" alt="" ID="{D7E26365-D0F8-4B56-BF2B-162C4932E53D}" coords="(0,382,1100,422)"/>
            <events title=""/>
          </entry>
          <entry title="%E6%9D%8E%E5%9B%9B%2Cli+si%2C10001%2C%E5%A5%B3%2C152xxxx1234%2Cxxx@xxx.com%2C+%E4%B8%8A%E6%B5%B71%E5%8C%BA%2C%E6%A0%A1%E5%8C%BA%E7%AE%A1%E7%90%86%E5%91%98%2C2017-03-11+10%3A30%3A12%2C2017-03-11+11%3A40%3A12">
            <area shape="0" alt="" ID="{DD47DEF9-5543-4E4A-8249-0156563BB216}" coords="(0,422,1100,462)"/>
            <events title=""/>
          </entry>
          <entry title="%E7%8E%8B%E4%BA%94%2Cwang+wu%2C10002%2C%E7%94%B7%2C+152xxxx1234%2Cxxx@xxx.com%2C%E4%B8%8A%E6%B5%B72%E5%8C%BA%2C%E8%80%81%E5%B8%88%2C2017-03-11+10%3A30%3A12%2C2017-03-11+11%3A40%3A12">
            <area shape="0" alt="" ID="{E92A136C-D644-427B-B5BF-35966E2363ED}" coords="(0,462,1100,502)"/>
            <events title=""/>
          </entry>
          <entry title="%E8%B5%B5%E5%85%AD%2Czhaoliu%2C10003%2C+%3A)%2C152xxxx1234%2Cxxx@xxx.com%2C%E5%A8%81%E6%B5%B7%2C%E5%AD%A6%E7%94%9F%2C2017-03-11+10%3A30%3A12">
            <area shape="0" alt="" ID="{20F30148-912B-45D8-BC35-147C216A2B26}" coords="(0,502,1100,542)"/>
            <events title=""/>
          </entry>
          <entry title="%E5%91%A8%E4%B8%83%2Czhouqi%2C10004%2C%3A)%2C152xxxx1234%2Cxxx@xxx.com%2C%E6%B1%9F%E8%8B%8F%2C%E5%AD%A6%E7%94%9F%2C2017-03-11+10%3A30%3A12%2C2017-03-11+11%3A40%3A12">
            <area shape="0" alt="" ID="{D8324FD1-A5D5-4209-A6ED-997EA8F3B8ED}" coords="(0,542,1100,582)"/>
            <events title=""/>
          </entry>
          <entry title="%E5%BC%A0%E4%B8%89%2C+zhang+san%2C10000%2C%E7%94%B7%2C152xxxx1234%2Cxxx@xxx.com%2C+%E6%80%BB%E9%83%A8%2C%E8%B6%85%E7%BA%A7%E7%AE%A1%E7%90%86%E5%91%98%2C2017-03-11+10%3A30%3A12%2C2017-03-11+11%3A40%3A12">
            <area shape="0" alt="" ID="{25B35EEB-75CF-459F-BF6C-AEEC85A90BBD}" coords="(0,582,1100,601)"/>
            <events title=""/>
          </entry>
          <entry title="%E6%9D%8E%E5%9B%9B%2Cli+si%2C10001%2C%E5%A5%B3%2C152xxxx1234%2Cxxx@xxx.com%2C+%E4%B8%8A%E6%B5%B71%E5%8C%BA%2C%E6%A0%A1%E5%8C%BA%E7%AE%A1%E7%90%86%E5%91%98%2C2017-03-11+10%3A30%3A12%2C2017-03-11+11%3A40%3A12">
            <area shape="0" alt="" ID="{19848990-B927-4431-913A-A06862CD2C0F}" coords="(0,0,0,0)"/>
            <events title=""/>
          </entry>
          <entry title="%E7%8E%8B%E4%BA%94%2Cwang+wu%2C10002%2C%E7%94%B7%2C+152xxxx1234%2Cxxx@xxx.com%2C%E4%B8%8A%E6%B5%B72%E5%8C%BA%2C%E8%80%81%E5%B8%88%2C2017-03-11+10%3A30%3A12%2C2017-03-11+11%3A40%3A12">
            <area shape="0" alt="" ID="{B726FD3D-2E01-428C-8354-F902B10B14E7}" coords="(0,0,0,0)"/>
            <events title=""/>
          </entry>
          <entry title="%E8%B5%B5%E5%85%AD%2Czhaoliu%2C10003%2C+%3A)%2C152xxxx1234%2Cxxx@xxx.com%2C%E5%A8%81%E6%B5%B7%2C%E5%AD%A6%E7%94%9F%2C2017-03-11+10%3A30%3A12">
            <area shape="0" alt="" ID="{BDF835FC-373E-4FFE-8A07-D9D31DD20B61}" coords="(0,0,0,0)"/>
            <events title=""/>
          </entry>
          <entry title="%E5%91%A8%E4%B8%83%2Czhouqi%2C10004%2C%3A)%2C152xxxx1234%2Cxxx@xxx.com%2C%E6%B1%9F%E8%8B%8F%2C%E5%AD%A6%E7%94%9F%2C2017-03-11+10%3A30%3A12%2C2017-03-11+11%3A40%3A12">
            <area shape="0" alt="" ID="{3C207E90-2009-4C65-8858-D00456A46E4C}" coords="(0,0,0,0)"/>
            <events title=""/>
          </entry>
        </interactiveData>
        <textSet textColor="4278190080" textSize="16" lineSpacingMultiple="1" textAlign="HaCenter" textVAlign="VaTop" textWordWrap="True" lineSpacing="21" textStyles="[]" useDefaultTextSize="False">
          <font family="%E5%BE%AE%E8%BD%AF%E9%9B%85%E9%BB%91" displayName="%E5%BE%AE%E8%BD%AF%E9%9B%85%E9%BB%91" postScript="" weightStyle="Regular" weight="400" isBold="False" isItalic="False"/>
          <text>%E5%A7%93%E5%90%8D+%5Ev%2C+%E8%8B%B1%E6%96%87%E5%90%8D+%5E%2C%E5%AD%A6%E5%8F%B7+%5Ev%2C%E6%80%A7%E5%88%AB+%5Ev%2C+%E6%89%8B%E6%9C%BA%E5%8F%B7%E7%A0%81%2C%E9%82%AE%E7%AE%B1%2C+%E6%A0%A1%E5%8C%BA+%5Ev%2C%E6%9D%83%E9%99%90+v%2C%E5%88%9B%E5%BB%BA%E6%97%B6%E9%97%B4+%5Ev%2C%E6%9C%80%E8%BF%91%E7%99%BB%E5%BD%95+%5Ev+%0D%0A%E5%BC%A0%E4%B8%89%2C+zhang+san%2C10000%2C%E7%94%B7%2C152xxxx1234%2Cxxx@xxx.com%2C+%E6%80%BB%E9%83%A8%2C%E8%B6%85%E7%BA%A7%E7%AE%A1%E7%90%86%E5%91%98%2C2017-03-11+10%3A30%3A12%2C2017-03-11+11%3A40%3A12%0D%0A%E6%9D%8E%E5%9B%9B%2Cli+si%2C10001%2C%E5%A5%B3%2C152xxxx1234%2Cxxx@xxx.com%2C+%E4%B8%8A%E6%B5%B71%E5%8C%BA%2C%E6%A0%A1%E5%8C%BA%E7%AE%A1%E7%90%86%E5%91%98%2C2017-03-11+10%3A30%3A12%2C2017-03-11+11%3A40%3A12%0D%0A%E7%8E%8B%E4%BA%94%2Cwang+wu%2C10002%2C%E7%94%B7%2C+152xxxx1234%2Cxxx@xxx.com%2C%E4%B8%8A%E6%B5%B72%E5%8C%BA%2C%E8%80%81%E5%B8%88%2C2017-03-11+10%3A30%3A12%2C2017-03-11+11%3A40%3A12%0D%0A%E8%B5%B5%E5%85%AD%2Czhaoliu%2C10003%2C+%3A)%2C152xxxx1234%2Cxxx@xxx.com%2C%E5%A8%81%E6%B5%B7%2C%E5%AD%A6%E7%94%9F%2C2017-03-11+10%3A30%3A12%0D%0A%E5%91%A8%E4%B8%83%2Czhouqi%2C10004%2C%3A)%2C152xxxx1234%2Cxxx@xxx.com%2C%E6%B1%9F%E8%8B%8F%2C%E5%AD%A6%E7%94%9F%2C2017-03-11+10%3A30%3A12%2C2017-03-11+11%3A40%3A12%0D%0A%E5%BC%A0%E4%B8%89%2C+zhang+san%2C10000%2C%E7%94%B7%2C152xxxx1234%2Cxxx@xxx.com%2C+%E6%80%BB%E9%83%A8%2C%E8%B6%85%E7%BA%A7%E7%AE%A1%E7%90%86%E5%91%98%2C2017-03-11+10%3A30%3A12%2C2017-03-11+11%3A40%3A12%0D%0A%E6%9D%8E%E5%9B%9B%2Cli+si%2C10001%2C%E5%A5%B3%2C152xxxx1234%2Cxxx@xxx.com%2C+%E4%B8%8A%E6%B5%B71%E5%8C%BA%2C%E6%A0%A1%E5%8C%BA%E7%AE%A1%E7%90%86%E5%91%98%2C2017-03-11+10%3A30%3A12%2C2017-03-11+11%3A40%3A12%0D%0A%E7%8E%8B%E4%BA%94%2Cwang+wu%2C10002%2C%E7%94%B7%2C+152xxxx1234%2Cxxx@xxx.com%2C%E4%B8%8A%E6%B5%B72%E5%8C%BA%2C%E8%80%81%E5%B8%88%2C2017-03-11+10%3A30%3A12%2C2017-03-11+11%3A40%3A12%0D%0A%E8%B5%B5%E5%85%AD%2Czhaoliu%2C10003%2C+%3A)%2C152xxxx1234%2Cxxx@xxx.com%2C%E5%A8%81%E6%B5%B7%2C%E5%AD%A6%E7%94%9F%2C2017-03-11+10%3A30%3A12%0D%0A%E5%91%A8%E4%B8%83%2Czhouqi%2C10004%2C%3A)%2C152xxxx1234%2Cxxx@xxx.com%2C%E6%B1%9F%E8%8B%8F%2C%E5%AD%A6%E7%94%9F%2C2017-03-11+10%3A30%3A12%2C2017-03-11+11%3A40%3A12%0D%0A%E6%9D%8E%E5%9B%9B%2Cli+si%2C10001%2C%E5%A5%B3%2C152xxxx1234%2Cxxx@xxx.com%2C+%E4%B8%8A%E6%B5%B71%E5%8C%BA%2C%E6%A0%A1%E5%8C%BA%E7%AE%A1%E7%90%86%E5%91%98%2C2017-03-11+10%3A30%3A12%2C2017-03-11+11%3A40%3A12%0D%0A%E7%8E%8B%E4%BA%94%2Cwang+wu%2C10002%2C%E7%94%B7%2C+152xxxx1234%2Cxxx@xxx.com%2C%E4%B8%8A%E6%B5%B72%E5%8C%BA%2C%E8%80%81%E5%B8%88%2C2017-03-11+10%3A30%3A12%2C2017-03-11+11%3A40%3A12%0D%0A%E8%B5%B5%E5%85%AD%2Czhaoliu%2C10003%2C+%3A)%2C152xxxx1234%2Cxxx@xxx.com%2C%E5%A8%81%E6%B5%B7%2C%E5%AD%A6%E7%94%9F%2C2017-03-11+10%3A30%3A12%0D%0A%E5%91%A8%E4%B8%83%2Czhouqi%2C10004%2C%3A)%2C152xxxx1234%2Cxxx@xxx.com%2C%E6%B1%9F%E8%8B%8F%2C%E5%AD%A6%E7%94%9F%2C2017-03-11+10%3A30%3A12%2C2017-03-11+11%3A40%3A12%0D%0A%E5%BC%A0%E4%B8%89%2C+zhang+san%2C10000%2C%E7%94%B7%2C152xxxx1234%2Cxxx@xxx.com%2C+%E6%80%BB%E9%83%A8%2C%E8%B6%85%E7%BA%A7%E7%AE%A1%E7%90%86%E5%91%98%2C2017-03-11+10%3A30%3A12%2C2017-03-11+11%3A40%3A12%0D%0A%E6%9D%8E%E5%9B%9B%2Cli+si%2C10001%2C%E5%A5%B3%2C152xxxx1234%2Cxxx@xxx.com%2C+%E4%B8%8A%E6%B5%B71%E5%8C%BA%2C%E6%A0%A1%E5%8C%BA%E7%AE%A1%E7%90%86%E5%91%98%2C2017-03-11+10%3A30%3A12%2C2017-03-11+11%3A40%3A12%0D%0A%E7%8E%8B%E4%BA%94%2Cwang+wu%2C10002%2C%E7%94%B7%2C+152xxxx1234%2Cxxx@xxx.com%2C%E4%B8%8A%E6%B5%B72%E5%8C%BA%2C%E8%80%81%E5%B8%88%2C2017-03-11+10%3A30%3A12%2C2017-03-11+11%3A40%3A12%0D%0A%E8%B5%B5%E5%85%AD%2Czhaoliu%2C10003%2C+%3A)%2C152xxxx1234%2Cxxx@xxx.com%2C%E5%A8%81%E6%B5%B7%2C%E5%AD%A6%E7%94%9F%2C2017-03-11+10%3A30%3A12%0D%0A%E5%91%A8%E4%B8%83%2Czhouqi%2C10004%2C%3A)%2C152xxxx1234%2Cxxx@xxx.com%2C%E6%B1%9F%E8%8B%8F%2C%E5%AD%A6%E7%94%9F%2C2017-03-11+10%3A30%3A12%2C2017-03-11+11%3A40%3A12</text>
        </textSet>
        <selectedIndex>0</selectedIndex>
        <selectedColor>4291611852</selectedColor>
        <textPadding>0</textPadding>
        <showVLine>True</showVLine>
        <showHLine>False</showHLine>
        <showHeader>True</showHeader>
        <interlaceColor>4293848814</interlaceColor>
        <itemHeight>40</itemHeight>
        <isInterlace>True</isInterlace>
        <separatorColor>4284900966</separatorColor>
        <columnRatio>{6.8,8.7,6.8,6.8,10.8,11.1,6.8,9.1,16.4,16.4}</columnRatio>
      </controlProperties>
    </control>
    <control controlID="B7233B87-6A48-4223-B28D-44A55A5D55ED" controlTypeID="Shape" isShow="True" caption="%E5%BD%A2%E7%8A%B6" x="0" y="726" w="200" h="37" measuredW="120" measuredH="100" zOrder="7" locked="False" sizeLocked="False">
      <controlProperties>
        <basic color="4294967295" borderVisible="False" borderColor="4284900966" isAutoSize="False" status="MsEnabled" opacity="1" isCommentCom="False" canMove="True" alias="" rotation="0"/>
        <states/>
        <verticalScrollbarShow>False</verticalScrollbarShow>
        <verticalScrollbarProgress>0</verticalScrollbarProgress>
        <horizontalScrollbarShow>False</horizontalScrollbarShow>
        <horizontalScrollbarProgress>0</horizontalScrollbarProgress>
        <links eventType="AtClick" animate="AmNone" animateAutoDelay="0" animateDuration="500">
          <link targetPageID="" linkType="ltPageLink" isApplyIncludePage="False" title="%E9%93%BE%E6%8E%A5">
            <area shape="0" alt="" ID="{7E06A13E-EFE1-4E35-B201-AA3296C59CED}" coords="(0,0,200,37)"/>
          </link>
        </links>
        <interactiveData>
          <entry title="">
            <area shape="0" alt="" ID="{891DC12F-D1DD-4A8D-A21D-C16605FF83DD}" coords="(0,0,200,37)"/>
            <events title=""/>
          </entry>
        </interactiveData>
        <textSet textColor="4278190080" textSize="14" lineSpacingMultiple="1" textAlign="HaCenter" textVAlign="VaMiddle" textWordWrap="True" lineSpacing="18" textStyles="[]" useDefaultTextSize="True">
          <font family="%E5%BE%AE%E8%BD%AF%E9%9B%85%E9%BB%91" displayName="%E5%BE%AE%E8%BD%AF%E9%9B%85%E9%BB%91" postScript="" weightStyle="Regular" weight="400" isBold="False" isItalic="False"/>
          <text>%E7%AC%AC+1+%E9%A1%B5%2C%E5%85%B1+80+%E9%A1%B5%2C+%E6%80%BB%E8%AE%A1+1595+%E4%BA%BA.</text>
        </textSet>
        <selectedIndex>-1</selectedIndex>
        <selectedColor>4282501083</selectedColor>
        <textPadding>0</textPadding>
        <shapeBorderType>SbRectangle</shapeBorderType>
        <triangleType>TdZero</triangleType>
        <dashMode>SdSolid</dashMode>
        <rectangleBorderLeftVisible>True</rectangleBorderLeftVisible>
        <rectangleBorderRightVisible>True</rectangleBorderRightVisible>
        <rectangleBorderTopVisible>True</rectangleBorderTopVisible>
        <rectangleBorderBottomVisible>True</rectangleBorderBottomVisible>
        <radius>0</radius>
        <radiusIsPercent>False</radiusIsPercent>
        <thickness>1</thickness>
      </controlProperties>
    </control>
    <control controlID="E36B680D-1F84-4471-999C-02D1BE4BA349" controlTypeID="Shape" isShow="True" caption="%E5%BD%A2%E7%8A%B6" x="670" y="732" w="66" h="24" measuredW="120" measuredH="100" zOrder="8" locked="False" sizeLocked="False">
      <controlProperties>
        <basic color="4294967295" borderVisible="True" borderColor="4284900966" isAutoSize="False" status="MsEnabled" opacity="1" isCommentCom="False" canMove="True" alias="" rotation="0"/>
        <states/>
        <verticalScrollbarShow>False</verticalScrollbarShow>
        <verticalScrollbarProgress>0</verticalScrollbarProgress>
        <horizontalScrollbarShow>False</horizontalScrollbarShow>
        <horizontalScrollbarProgress>0</horizontalScrollbarProgress>
        <links eventType="AtClick" animate="AmNone" animateAutoDelay="0" animateDuration="500">
          <link targetPageID="" linkType="ltPageLink" isApplyIncludePage="False" title="%E9%93%BE%E6%8E%A5">
            <area shape="0" alt="" ID="{3BA93A6A-2237-4EB6-A405-9C3B5E432826}" coords="(0,0,66,24)"/>
          </link>
        </links>
        <interactiveData>
          <entry title="">
            <area shape="0" alt="" ID="{80F0C089-65BC-4755-B51C-55C793D2DD75}" coords="(0,0,66,24)"/>
            <events title=""/>
          </entry>
        </interactiveData>
        <textSet textColor="4280968342" textSize="14" lineSpacingMultiple="1" textAlign="HaCenter" textVAlign="VaMiddle" textWordWrap="True" lineSpacing="18" textStyles="[]" useDefaultTextSize="True">
          <font family="%E5%BE%AE%E8%BD%AF%E9%9B%85%E9%BB%91" displayName="%E5%BE%AE%E8%BD%AF%E9%9B%85%E9%BB%91" postScript="" weightStyle="Regular" weight="400" isBold="False" isItalic="False"/>
          <text>%E9%A6%96%E9%A1%B5</text>
        </textSet>
        <selectedIndex>-1</selectedIndex>
        <selectedColor>4282501083</selectedColor>
        <textPadding>0</textPadding>
        <shapeBorderType>SbRectangle</shapeBorderType>
        <triangleType>TdZero</triangleType>
        <dashMode>SdSolid</dashMode>
        <rectangleBorderLeftVisible>True</rectangleBorderLeftVisible>
        <rectangleBorderRightVisible>True</rectangleBorderRightVisible>
        <rectangleBorderTopVisible>True</rectangleBorderTopVisible>
        <rectangleBorderBottomVisible>True</rectangleBorderBottomVisible>
        <radius>12</radius>
        <radiusIsPercent>False</radiusIsPercent>
        <thickness>1</thickness>
      </controlProperties>
    </control>
    <control controlID="8A6003D6-3651-4215-900B-F08AE16A4255" controlTypeID="Shape" isShow="True" caption="%E5%BD%A2%E7%8A%B6" x="743" y="732" w="66" h="24" measuredW="120" measuredH="100" zOrder="9" locked="False" sizeLocked="False">
      <controlProperties>
        <basic color="4294967295" borderVisible="True" borderColor="4284900966" isAutoSize="False" status="MsEnabled" opacity="1" isCommentCom="False" canMove="True" alias="" rotation="0"/>
        <states/>
        <verticalScrollbarShow>False</verticalScrollbarShow>
        <verticalScrollbarProgress>0</verticalScrollbarProgress>
        <horizontalScrollbarShow>False</horizontalScrollbarShow>
        <horizontalScrollbarProgress>0</horizontalScrollbarProgress>
        <links eventType="AtClick" animate="AmNone" animateAutoDelay="0" animateDuration="500">
          <link targetPageID="" linkType="ltPageLink" isApplyIncludePage="False" title="%E9%93%BE%E6%8E%A5">
            <area shape="0" alt="" ID="{3BA93A6A-2237-4EB6-A405-9C3B5E432826}" coords="(0,0,66,24)"/>
          </link>
        </links>
        <interactiveData>
          <entry title="">
            <area shape="0" alt="" ID="{80F0C089-65BC-4755-B51C-55C793D2DD75}" coords="(0,0,66,24)"/>
            <events title=""/>
          </entry>
        </interactiveData>
        <textSet textColor="4288256409" textSize="14" lineSpacingMultiple="1" textAlign="HaCenter" textVAlign="VaMiddle" textWordWrap="True" lineSpacing="18" textStyles="[]" useDefaultTextSize="True">
          <font family="%E5%BE%AE%E8%BD%AF%E9%9B%85%E9%BB%91" displayName="%E5%BE%AE%E8%BD%AF%E9%9B%85%E9%BB%91" postScript="" weightStyle="Regular" weight="400" isBold="False" isItalic="False"/>
          <text>%E4%B8%8A%E4%B8%80%E9%A1%B5</text>
        </textSet>
        <selectedIndex>-1</selectedIndex>
        <selectedColor>4282501083</selectedColor>
        <textPadding>0</textPadding>
        <shapeBorderType>SbRectangle</shapeBorderType>
        <triangleType>TdZero</triangleType>
        <dashMode>SdSolid</dashMode>
        <rectangleBorderLeftVisible>True</rectangleBorderLeftVisible>
        <rectangleBorderRightVisible>True</rectangleBorderRightVisible>
        <rectangleBorderTopVisible>True</rectangleBorderTopVisible>
        <rectangleBorderBottomVisible>True</rectangleBorderBottomVisible>
        <radius>12</radius>
        <radiusIsPercent>False</radiusIsPercent>
        <thickness>1</thickness>
      </controlProperties>
    </control>
    <control controlID="BE9B9C48-8619-4E99-8FC0-F1EEFCA2F8CC" controlTypeID="Shape" isShow="True" caption="%E5%BD%A2%E7%8A%B6" x="962" y="732" w="66" h="24" measuredW="120" measuredH="100" zOrder="10" locked="False" sizeLocked="False">
      <controlProperties>
        <basic color="4294967295" borderVisible="True" borderColor="4284900966" isAutoSize="False" status="MsEnabled" opacity="1" isCommentCom="False" canMove="True" alias="" rotation="0"/>
        <states/>
        <verticalScrollbarShow>False</verticalScrollbarShow>
        <verticalScrollbarProgress>0</verticalScrollbarProgress>
        <horizontalScrollbarShow>False</horizontalScrollbarShow>
        <horizontalScrollbarProgress>0</horizontalScrollbarProgress>
        <links eventType="AtClick" animate="AmNone" animateAutoDelay="0" animateDuration="500">
          <link targetPageID="" linkType="ltPageLink" isApplyIncludePage="False" title="%E9%93%BE%E6%8E%A5">
            <area shape="0" alt="" ID="{3BA93A6A-2237-4EB6-A405-9C3B5E432826}" coords="(0,0,66,24)"/>
          </link>
        </links>
        <interactiveData>
          <entry title="">
            <area shape="0" alt="" ID="{80F0C089-65BC-4755-B51C-55C793D2DD75}" coords="(0,0,66,24)"/>
            <events title=""/>
          </entry>
        </interactiveData>
        <textSet textColor="4280968342" textSize="14" lineSpacingMultiple="1" textAlign="HaCenter" textVAlign="VaMiddle" textWordWrap="True" lineSpacing="18" textStyles="[]" useDefaultTextSize="True">
          <font family="%E5%BE%AE%E8%BD%AF%E9%9B%85%E9%BB%91" displayName="%E5%BE%AE%E8%BD%AF%E9%9B%85%E9%BB%91" postScript="" weightStyle="Regular" weight="400" isBold="False" isItalic="False"/>
          <text>%E4%B8%8B%E4%B8%80%E9%A1%B5</text>
        </textSet>
        <selectedIndex>-1</selectedIndex>
        <selectedColor>4282501083</selectedColor>
        <textPadding>0</textPadding>
        <shapeBorderType>SbRectangle</shapeBorderType>
        <triangleType>TdZero</triangleType>
        <dashMode>SdSolid</dashMode>
        <rectangleBorderLeftVisible>True</rectangleBorderLeftVisible>
        <rectangleBorderRightVisible>True</rectangleBorderRightVisible>
        <rectangleBorderTopVisible>True</rectangleBorderTopVisible>
        <rectangleBorderBottomVisible>True</rectangleBorderBottomVisible>
        <radius>12</radius>
        <radiusIsPercent>False</radiusIsPercent>
        <thickness>1</thickness>
      </controlProperties>
    </control>
    <control controlID="663D0375-057C-4DC5-995D-91A0B4560CEA" controlTypeID="Shape" isShow="True" caption="%E5%BD%A2%E7%8A%B6" x="1031" y="732" w="66" h="24" measuredW="120" measuredH="100" zOrder="11" locked="False" sizeLocked="False">
      <controlProperties>
        <basic color="4294967295" borderVisible="True" borderColor="4284900966" isAutoSize="False" status="MsEnabled" opacity="1" isCommentCom="False" canMove="True" alias="" rotation="0"/>
        <states/>
        <verticalScrollbarShow>False</verticalScrollbarShow>
        <verticalScrollbarProgress>0</verticalScrollbarProgress>
        <horizontalScrollbarShow>False</horizontalScrollbarShow>
        <horizontalScrollbarProgress>0</horizontalScrollbarProgress>
        <links eventType="AtClick" animate="AmNone" animateAutoDelay="0" animateDuration="500">
          <link targetPageID="" linkType="ltPageLink" isApplyIncludePage="False" title="%E9%93%BE%E6%8E%A5">
            <area shape="0" alt="" ID="{3BA93A6A-2237-4EB6-A405-9C3B5E432826}" coords="(0,0,66,24)"/>
          </link>
        </links>
        <interactiveData>
          <entry title="">
            <area shape="0" alt="" ID="{80F0C089-65BC-4755-B51C-55C793D2DD75}" coords="(0,0,66,24)"/>
            <events title=""/>
          </entry>
        </interactiveData>
        <textSet textColor="4280968342" textSize="14" lineSpacingMultiple="1" textAlign="HaCenter" textVAlign="VaMiddle" textWordWrap="True" lineSpacing="18" textStyles="[]" useDefaultTextSize="True">
          <font family="%E5%BE%AE%E8%BD%AF%E9%9B%85%E9%BB%91" displayName="%E5%BE%AE%E8%BD%AF%E9%9B%85%E9%BB%91" postScript="" weightStyle="Regular" weight="400" isBold="False" isItalic="False"/>
          <text>%E5%B0%BE%E9%A1%B5</text>
        </textSet>
        <selectedIndex>-1</selectedIndex>
        <selectedColor>4282501083</selectedColor>
        <textPadding>0</textPadding>
        <shapeBorderType>SbRectangle</shapeBorderType>
        <triangleType>TdZero</triangleType>
        <dashMode>SdSolid</dashMode>
        <rectangleBorderLeftVisible>True</rectangleBorderLeftVisible>
        <rectangleBorderRightVisible>True</rectangleBorderRightVisible>
        <rectangleBorderTopVisible>True</rectangleBorderTopVisible>
        <rectangleBorderBottomVisible>True</rectangleBorderBottomVisible>
        <radius>12</radius>
        <radiusIsPercent>False</radiusIsPercent>
        <thickness>1</thickness>
      </controlProperties>
    </control>
    <control controlID="C359E0E9-6BDA-4603-90DE-3EFE49114758" controlTypeID="Shape" isShow="True" caption="%E5%BD%A2%E7%8A%B6" x="815" y="732" w="26" h="24" measuredW="120" measuredH="100" zOrder="12" locked="False" sizeLocked="False">
      <controlProperties>
        <basic color="4291611852" borderVisible="True" borderColor="4281558783" isAutoSize="False" status="MsEnabled" opacity="1" isCommentCom="False" canMove="True" alias="" rotation="0"/>
        <states/>
        <verticalScrollbarShow>False</verticalScrollbarShow>
        <verticalScrollbarProgress>0</verticalScrollbarProgress>
        <horizontalScrollbarShow>False</horizontalScrollbarShow>
        <horizontalScrollbarProgress>0</horizontalScrollbarProgress>
        <links eventType="AtClick" animate="AmNone" animateAutoDelay="0" animateDuration="500">
          <link targetPageID="" linkType="ltPageLink" isApplyIncludePage="False" title="%E9%93%BE%E6%8E%A5">
            <area shape="0" alt="" ID="{3BA93A6A-2237-4EB6-A405-9C3B5E432826}" coords="(0,0,26,24)"/>
          </link>
        </links>
        <interactiveData>
          <entry title="">
            <area shape="0" alt="" ID="{80F0C089-65BC-4755-B51C-55C793D2DD75}" coords="(0,0,26,24)"/>
            <events title=""/>
          </entry>
        </interactiveData>
        <textSet textColor="4280968342" textSize="14" lineSpacingMultiple="1" textAlign="HaCenter" textVAlign="VaMiddle" textWordWrap="True" lineSpacing="18" textStyles="[]" useDefaultTextSize="True">
          <font family="%E5%BE%AE%E8%BD%AF%E9%9B%85%E9%BB%91" displayName="%E5%BE%AE%E8%BD%AF%E9%9B%85%E9%BB%91" postScript="" weightStyle="Regular" weight="400" isBold="False" isItalic="False"/>
          <text>1</text>
        </textSet>
        <selectedIndex>-1</selectedIndex>
        <selectedColor>4282501083</selectedColor>
        <textPadding>0</textPadding>
        <shapeBorderType>SbEllipse</shapeBorderType>
        <triangleType>TdZero</triangleType>
        <dashMode>SdSolid</dashMode>
        <rectangleBorderLeftVisible>True</rectangleBorderLeftVisible>
        <rectangleBorderRightVisible>True</rectangleBorderRightVisible>
        <rectangleBorderTopVisible>True</rectangleBorderTopVisible>
        <rectangleBorderBottomVisible>True</rectangleBorderBottomVisible>
        <radius>12</radius>
        <radiusIsPercent>False</radiusIsPercent>
        <thickness>1</thickness>
      </controlProperties>
    </control>
    <control controlID="1FC39B07-EE31-444B-B91A-B4B4F8863EAA" controlTypeID="Shape" isShow="True" caption="%E5%BD%A2%E7%8A%B6" x="842" y="732" w="26" h="24" measuredW="120" measuredH="100" zOrder="13" locked="False" sizeLocked="False">
      <controlProperties>
        <basic color="4294967295" borderVisible="True" borderColor="4284900966" isAutoSize="False" status="MsEnabled" opacity="1" isCommentCom="False" canMove="True" alias="" rotation="0"/>
        <states/>
        <verticalScrollbarShow>False</verticalScrollbarShow>
        <verticalScrollbarProgress>0</verticalScrollbarProgress>
        <horizontalScrollbarShow>False</horizontalScrollbarShow>
        <horizontalScrollbarProgress>0</horizontalScrollbarProgress>
        <links eventType="AtClick" animate="AmNone" animateAutoDelay="0" animateDuration="500">
          <link targetPageID="" linkType="ltPageLink" isApplyIncludePage="False" title="%E9%93%BE%E6%8E%A5">
            <area shape="0" alt="" ID="{3BA93A6A-2237-4EB6-A405-9C3B5E432826}" coords="(0,0,26,24)"/>
          </link>
        </links>
        <interactiveData>
          <entry title="">
            <area shape="0" alt="" ID="{80F0C089-65BC-4755-B51C-55C793D2DD75}" coords="(0,0,26,24)"/>
            <events title=""/>
          </entry>
        </interactiveData>
        <textSet textColor="4280968342" textSize="14" lineSpacingMultiple="1" textAlign="HaCenter" textVAlign="VaMiddle" textWordWrap="True" lineSpacing="18" textStyles="[]" useDefaultTextSize="True">
          <font family="%E5%BE%AE%E8%BD%AF%E9%9B%85%E9%BB%91" displayName="%E5%BE%AE%E8%BD%AF%E9%9B%85%E9%BB%91" postScript="" weightStyle="Regular" weight="400" isBold="False" isItalic="False"/>
          <text>2</text>
        </textSet>
        <selectedIndex>-1</selectedIndex>
        <selectedColor>4282501083</selectedColor>
        <textPadding>0</textPadding>
        <shapeBorderType>SbEllipse</shapeBorderType>
        <triangleType>TdZero</triangleType>
        <dashMode>SdSolid</dashMode>
        <rectangleBorderLeftVisible>True</rectangleBorderLeftVisible>
        <rectangleBorderRightVisible>True</rectangleBorderRightVisible>
        <rectangleBorderTopVisible>True</rectangleBorderTopVisible>
        <rectangleBorderBottomVisible>True</rectangleBorderBottomVisible>
        <radius>12</radius>
        <radiusIsPercent>False</radiusIsPercent>
        <thickness>1</thickness>
      </controlProperties>
    </control>
    <control controlID="9F76D48B-CC68-44C8-B0CF-063F05395D13" controlTypeID="Shape" isShow="True" caption="%E5%BD%A2%E7%8A%B6" x="907" y="732" w="26" h="24" measuredW="120" measuredH="100" zOrder="14" locked="False" sizeLocked="False">
      <controlProperties>
        <basic color="4294967295" borderVisible="True" borderColor="4284900966" isAutoSize="False" status="MsEnabled" opacity="1" isCommentCom="False" canMove="True" alias="" rotation="0"/>
        <states/>
        <verticalScrollbarShow>False</verticalScrollbarShow>
        <verticalScrollbarProgress>0</verticalScrollbarProgress>
        <horizontalScrollbarShow>False</horizontalScrollbarShow>
        <horizontalScrollbarProgress>0</horizontalScrollbarProgress>
        <links eventType="AtClick" animate="AmNone" animateAutoDelay="0" animateDuration="500">
          <link targetPageID="" linkType="ltPageLink" isApplyIncludePage="False" title="%E9%93%BE%E6%8E%A5">
            <area shape="0" alt="" ID="{3BA93A6A-2237-4EB6-A405-9C3B5E432826}" coords="(0,0,26,24)"/>
          </link>
        </links>
        <interactiveData>
          <entry title="">
            <area shape="0" alt="" ID="{80F0C089-65BC-4755-B51C-55C793D2DD75}" coords="(0,0,26,24)"/>
            <events title=""/>
          </entry>
        </interactiveData>
        <textSet textColor="4280968342" textSize="14" lineSpacingMultiple="1" textAlign="HaCenter" textVAlign="VaMiddle" textWordWrap="True" lineSpacing="18" textStyles="[]" useDefaultTextSize="True">
          <font family="%E5%BE%AE%E8%BD%AF%E9%9B%85%E9%BB%91" displayName="%E5%BE%AE%E8%BD%AF%E9%9B%85%E9%BB%91" postScript="" weightStyle="Regular" weight="400" isBold="False" isItalic="False"/>
          <text>79</text>
        </textSet>
        <selectedIndex>-1</selectedIndex>
        <selectedColor>4282501083</selectedColor>
        <textPadding>0</textPadding>
        <shapeBorderType>SbEllipse</shapeBorderType>
        <triangleType>TdZero</triangleType>
        <dashMode>SdSolid</dashMode>
        <rectangleBorderLeftVisible>True</rectangleBorderLeftVisible>
        <rectangleBorderRightVisible>True</rectangleBorderRightVisible>
        <rectangleBorderTopVisible>True</rectangleBorderTopVisible>
        <rectangleBorderBottomVisible>True</rectangleBorderBottomVisible>
        <radius>12</radius>
        <radiusIsPercent>False</radiusIsPercent>
        <thickness>1</thickness>
      </controlProperties>
    </control>
    <control controlID="6A98913A-262B-4B45-8751-3F0077A6EE0D" controlTypeID="Shape" isShow="True" caption="%E5%BD%A2%E7%8A%B6" x="933" y="732" w="26" h="24" measuredW="120" measuredH="100" zOrder="15" locked="False" sizeLocked="False">
      <controlProperties>
        <basic color="4294967295" borderVisible="True" borderColor="4284900966" isAutoSize="False" status="MsEnabled" opacity="1" isCommentCom="False" canMove="True" alias="" rotation="0"/>
        <states/>
        <verticalScrollbarShow>False</verticalScrollbarShow>
        <verticalScrollbarProgress>0</verticalScrollbarProgress>
        <horizontalScrollbarShow>False</horizontalScrollbarShow>
        <horizontalScrollbarProgress>0</horizontalScrollbarProgress>
        <links eventType="AtClick" animate="AmNone" animateAutoDelay="0" animateDuration="500">
          <link targetPageID="" linkType="ltPageLink" isApplyIncludePage="False" title="%E9%93%BE%E6%8E%A5">
            <area shape="0" alt="" ID="{3BA93A6A-2237-4EB6-A405-9C3B5E432826}" coords="(0,0,26,24)"/>
          </link>
        </links>
        <interactiveData>
          <entry title="">
            <area shape="0" alt="" ID="{80F0C089-65BC-4755-B51C-55C793D2DD75}" coords="(0,0,26,24)"/>
            <events title=""/>
          </entry>
        </interactiveData>
        <textSet textColor="4280968342" textSize="14" lineSpacingMultiple="1" textAlign="HaCenter" textVAlign="VaMiddle" textWordWrap="True" lineSpacing="18" textStyles="[]" useDefaultTextSize="True">
          <font family="%E5%BE%AE%E8%BD%AF%E9%9B%85%E9%BB%91" displayName="%E5%BE%AE%E8%BD%AF%E9%9B%85%E9%BB%91" postScript="" weightStyle="Regular" weight="400" isBold="False" isItalic="False"/>
          <text>80</text>
        </textSet>
        <selectedIndex>-1</selectedIndex>
        <selectedColor>4282501083</selectedColor>
        <textPadding>0</textPadding>
        <shapeBorderType>SbEllipse</shapeBorderType>
        <triangleType>TdZero</triangleType>
        <dashMode>SdSolid</dashMode>
        <rectangleBorderLeftVisible>True</rectangleBorderLeftVisible>
        <rectangleBorderRightVisible>True</rectangleBorderRightVisible>
        <rectangleBorderTopVisible>True</rectangleBorderTopVisible>
        <rectangleBorderBottomVisible>True</rectangleBorderBottomVisible>
        <radius>12</radius>
        <radiusIsPercent>False</radiusIsPercent>
        <thickness>1</thickness>
      </controlProperties>
    </control>
    <control controlID="4DB87322-D295-46A7-8009-57363FA5292D" controlTypeID="Shape" isShow="True" caption="%E5%BD%A2%E7%8A%B6" x="505" y="20" w="349" h="96" measuredW="120" measuredH="100" zOrder="16" locked="False" sizeLocked="False">
      <controlProperties>
        <basic color="16777215" borderVisible="False" borderColor="4284900966" isAutoSize="False" status="MsEnabled" opacity="1" isCommentCom="False" canMove="True" alias="" rotation="0"/>
        <states/>
        <verticalScrollbarShow>False</verticalScrollbarShow>
        <verticalScrollbarProgress>0</verticalScrollbarProgress>
        <horizontalScrollbarShow>False</horizontalScrollbarShow>
        <horizontalScrollbarProgress>0</horizontalScrollbarProgress>
        <links eventType="AtClick" animate="AmNone" animateAutoDelay="0" animateDuration="500">
          <link targetPageID="" linkType="ltPageLink" isApplyIncludePage="False" title="%E9%93%BE%E6%8E%A5">
            <area shape="0" alt="" ID="{D33189AA-6F27-4F19-96F0-20E4E6B3E4F7}" coords="(0,0,349,96)"/>
          </link>
        </links>
        <interactiveData>
          <entry title="">
            <area shape="0" alt="" ID="{E5CC0AA6-18F8-42C0-8E9D-7B2055A188C1}" coords="(0,0,349,96)"/>
            <events title=""/>
          </entry>
        </interactiveData>
        <textSet textColor="4281584640" textSize="14" lineSpacingMultiple="1" textAlign="HaCenter" textVAlign="VaMiddle" textWordWrap="True" lineSpacing="18" textStyles="[]" useDefaultTextSize="True">
          <font family="%E5%BE%AE%E8%BD%AF%E9%9B%85%E9%BB%91" displayName="%E5%BE%AE%E8%BD%AF%E9%9B%85%E9%BB%91" postScript="" weightStyle="Regular" weight="400" isBold="False" isItalic="False"/>
          <text>PS%3A+%E5%90%84%E4%B8%AA%E7%AE%A1%E7%90%86%E5%91%98%E6%8B%A5%E6%9C%89%E4%B8%8D%E4%B8%80%E6%A0%B7%E7%9A%84%E6%9F%A5%E7%9C%8B%E6%9D%83%E9%99%90%EF%BC%8C%E6%80%BB%E9%83%A8%E8%B6%85%E7%BA%A7%E7%AE%A1%E7%90%86%E5%91%98%E5%8F%AF%E4%BB%A5%E6%9F%A5%E7%9C%8B%E5%85%A8%E9%83%A8%EF%BC%8C%E6%A0%A1%E5%8C%BA%E7%AE%A1%E7%90%86%E5%91%98%E5%8F%AA%E8%83%BD%E6%9F%A5%E7%9C%8B%E6%9C%AC%E6%A0%A1%E5%8C%BA%0D%0A%E7%AE%A1%E7%90%86%E6%A0%A1%E5%8C%BA%EF%BC%9A%E5%A6%82%E6%9E%9C%E6%98%AF%E8%B6%85%E7%BA%A7%E7%AE%A1%E7%90%86%E5%91%98%E5%88%99%E8%BF%9B%E5%85%A5%E5%88%B0%E6%A0%A1%E5%8C%BA%E7%AE%A1%E7%90%86%E9%A1%B5%E9%9D%A2%EF%BC%8C%E5%A6%82%E6%9E%9C%E6%98%AF%E6%A0%A1%E5%8C%BA%E7%AE%A1%E7%90%86%E5%91%98%E5%88%99%E8%BF%9B%E5%85%A5%E5%88%B0%E6%A0%A1%E5%8C%BA%E4%BF%A1%E6%81%AF%E8%AE%BE%E7%BD%AE%E9%A1%B5%E9%9D%A2</text>
        </textSet>
        <selectedIndex>-1</selectedIndex>
        <selectedColor>4282501083</selectedColor>
        <textPadding>0</textPadding>
        <shapeBorderType>SbRectangle</shapeBorderType>
        <triangleType>TdZero</triangleType>
        <dashMode>SdSolid</dashMode>
        <rectangleBorderLeftVisible>True</rectangleBorderLeftVisible>
        <rectangleBorderRightVisible>True</rectangleBorderRightVisible>
        <rectangleBorderTopVisible>True</rectangleBorderTopVisible>
        <rectangleBorderBottomVisible>True</rectangleBorderBottomVisible>
        <radius>0</radius>
        <radiusIsPercent>False</radiusIsPercent>
        <thickness>1</thickness>
      </controlProperties>
    </control>
    <control controlID="D4270BCF-4D1F-415A-901B-8FD0D78ABAF6" controlTypeID="Shape" isShow="True" caption="%E5%BD%A2%E7%8A%B6" x="917" y="82" w="78" h="29" measuredW="120" measuredH="100" zOrder="17" locked="False" sizeLocked="False">
      <controlProperties>
        <basic color="4281571737" borderVisible="True" borderColor="4284900966" isAutoSize="False" status="MsEnabled" opacity="1" isCommentCom="False" canMove="True" alias="" rotation="0"/>
        <states/>
        <verticalScrollbarShow>False</verticalScrollbarShow>
        <verticalScrollbarProgress>0</verticalScrollbarProgress>
        <horizontalScrollbarShow>False</horizontalScrollbarShow>
        <horizontalScrollbarProgress>0</horizontalScrollbarProgress>
        <links eventType="AtClick" animate="AmNone" animateAutoDelay="0" animateDuration="500">
          <link targetPageID="2FE62421-146B-400B-9AD6-ABF58AA4046A" linkType="ltPageLink" isApplyIncludePage="False" title="Add_zone">
            <area shape="0" alt="" ID="{6D46BA54-05EE-4105-B54B-609BBA199F11}" coords="(0,0,78,29)"/>
          </link>
        </links>
        <interactiveData>
          <entry title="">
            <area shape="0" alt="" ID="{8CA9F309-5D63-401B-854D-CA473DB9789E}" coords="(0,0,78,29)"/>
            <events title=""/>
          </entry>
        </interactiveData>
        <textSet textColor="4278190080" textSize="14" lineSpacingMultiple="1" textAlign="HaCenter" textVAlign="VaMiddle" textWordWrap="True" lineSpacing="18" textStyles="[]" useDefaultTextSize="True">
          <font family="%E5%BE%AE%E8%BD%AF%E9%9B%85%E9%BB%91" displayName="%E5%BE%AE%E8%BD%AF%E9%9B%85%E9%BB%91" postScript="" weightStyle="Regular" weight="400" isBold="False" isItalic="False"/>
          <text>%E6%A0%A1%E5%8C%BA%E7%AE%A1%E7%90%86</text>
        </textSet>
        <selectedIndex>-1</selectedIndex>
        <selectedColor>4282501083</selectedColor>
        <textPadding>0</textPadding>
        <shapeBorderType>SbRectangle</shapeBorderType>
        <triangleType>TdZero</triangleType>
        <dashMode>SdSolid</dashMode>
        <rectangleBorderLeftVisible>True</rectangleBorderLeftVisible>
        <rectangleBorderRightVisible>True</rectangleBorderRightVisible>
        <rectangleBorderTopVisible>True</rectangleBorderTopVisible>
        <rectangleBorderBottomVisible>True</rectangleBorderBottomVisible>
        <radius>4</radius>
        <radiusIsPercent>False</radiusIsPercent>
        <thickness>1</thickness>
      </controlProperties>
    </control>
    <control controlID="54ED34D4-22E2-454E-A2BD-20A5443751F9" controlTypeID="Shape" isShow="True" caption="%E5%BD%A2%E7%8A%B6" x="873" y="730" w="32" h="27" measuredW="120" measuredH="100" zOrder="18" locked="False" sizeLocked="False">
      <controlProperties>
        <basic color="4294967295" borderVisible="True" borderColor="4284900966" isAutoSize="False" status="MsEnabled" opacity="1" isCommentCom="False" canMove="True" alias="" rotation="0"/>
        <states/>
        <verticalScrollbarShow>False</verticalScrollbarShow>
        <verticalScrollbarProgress>0</verticalScrollbarProgress>
        <horizontalScrollbarShow>False</horizontalScrollbarShow>
        <horizontalScrollbarProgress>0</horizontalScrollbarProgress>
        <links eventType="AtClick" animate="AmNone" animateAutoDelay="0" animateDuration="500">
          <link targetPageID="" linkType="ltPageLink" isApplyIncludePage="False" title="%E9%93%BE%E6%8E%A5">
            <area shape="0" alt="" ID="{2C3B781F-056F-40B7-90B0-3C6EC1C2979C}" coords="(0,0,32,27)"/>
          </link>
        </links>
        <interactiveData>
          <entry title="">
            <area shape="0" alt="" ID="{7851110D-AC8E-4D7E-ADB7-FB2975530C07}" coords="(0,0,32,27)"/>
            <events title=""/>
          </entry>
        </interactiveData>
        <textSet textColor="4278190080" textSize="14" lineSpacingMultiple="1" textAlign="HaCenter" textVAlign="VaMiddle" textWordWrap="True" lineSpacing="18" textStyles="[]" useDefaultTextSize="True">
          <font family="%E5%BE%AE%E8%BD%AF%E9%9B%85%E9%BB%91" displayName="%E5%BE%AE%E8%BD%AF%E9%9B%85%E9%BB%91" postScript="" weightStyle="Regular" weight="400" isBold="False" isItalic="False"/>
          <text>...</text>
        </textSet>
        <selectedIndex>0</selectedIndex>
        <selectedColor>4282501083</selectedColor>
        <textPadding>0</textPadding>
        <shapeBorderType>SbRectangle</shapeBorderType>
        <triangleType>TdZero</triangleType>
        <dashMode>SdSolid</dashMode>
        <rectangleBorderLeftVisible>True</rectangleBorderLeftVisible>
        <rectangleBorderRightVisible>True</rectangleBorderRightVisible>
        <rectangleBorderTopVisible>True</rectangleBorderTopVisible>
        <rectangleBorderBottomVisible>True</rectangleBorderBottomVisible>
        <radius>8</radius>
        <radiusIsPercent>False</radiusIsPercent>
        <thickness>1</thickness>
      </controlProperties>
    </control>
    <control controlID="BC79B116-6CDB-467C-9142-D3F6DC79B10B" controlTypeID="Shape" isShow="True" caption="%E5%BD%A2%E7%8A%B6" x="860" y="765" w="120" h="34" measuredW="120" measuredH="100" zOrder="19" locked="False" sizeLocked="False">
      <controlProperties>
        <basic color="16777215" borderVisible="False" borderColor="4284900966" isAutoSize="False" status="MsEnabled" opacity="1" isCommentCom="False" canMove="True" alias="" rotation="0"/>
        <states/>
        <verticalScrollbarShow>False</verticalScrollbarShow>
        <verticalScrollbarProgress>0</verticalScrollbarProgress>
        <horizontalScrollbarShow>False</horizontalScrollbarShow>
        <horizontalScrollbarProgress>0</horizontalScrollbarProgress>
        <links eventType="AtClick" animate="AmNone" animateAutoDelay="0" animateDuration="500">
          <link targetPageID="" linkType="ltPageLink" isApplyIncludePage="False" title="%E9%93%BE%E6%8E%A5">
            <area shape="0" alt="" ID="{35550006-A984-4DE9-BB80-B538FFD5146C}" coords="(0,0,120,34)"/>
          </link>
        </links>
        <interactiveData>
          <entry title="">
            <area shape="0" alt="" ID="{6BD3B499-C63A-4E13-82C2-E5AA4149ABE4}" coords="(0,0,120,34)"/>
            <events title=""/>
          </entry>
        </interactiveData>
        <textSet textColor="4294953984" textSize="14" lineSpacingMultiple="1" textAlign="HaCenter" textVAlign="VaMiddle" textWordWrap="True" lineSpacing="18" textStyles="[]" useDefaultTextSize="True">
          <font family="%E5%BE%AE%E8%BD%AF%E9%9B%85%E9%BB%91" displayName="%E5%BE%AE%E8%BD%AF%E9%9B%85%E9%BB%91" postScript="" weightStyle="Regular" weight="400" isBold="False" isItalic="False"/>
          <text>PS%3A%E6%AD%A4%E5%A4%84%E5%8F%AF%E4%BB%A5%E8%BE%93%E5%85%A5%E9%A1%B5%E6%95%B0%EF%BC%8C%E5%9B%9E%E8%BD%A6%E8%B7%B3%E8%BD%AC</text>
        </textSet>
        <selectedIndex>0</selectedIndex>
        <selectedColor>4282501083</selectedColor>
        <textPadding>0</textPadding>
        <shapeBorderType>SbRectangle</shapeBorderType>
        <triangleType>TdZero</triangleType>
        <dashMode>SdSolid</dashMode>
        <rectangleBorderLeftVisible>True</rectangleBorderLeftVisible>
        <rectangleBorderRightVisible>True</rectangleBorderRightVisible>
        <rectangleBorderTopVisible>True</rectangleBorderTopVisible>
        <rectangleBorderBottomVisible>True</rectangleBorderBottomVisible>
        <radius>0</radius>
        <radiusIsPercent>False</radiusIsPercent>
        <thickness>1</thickness>
      </controlProperties>
    </control>
  </controls>
  <param>
    <backgroundColor>4294967295</backgroundColor>
    <fontSize>0</fontSize>
    <fontFamily/>
    <guideLines/>
  </param>
</mockup>